pytest_verify/__init__.py
pytest_verify/plugin.py
pytest_verify/py.typed
pytest_verify-1.1.1.dist-info/licenses/LICENSE
pytest_verify-1.1.1.dist-info/METADATA
pytest_verify-1.1.1.dist-info/WHEEL
pytest_verify-1.1.1.dist-info/entry_points.txt
pytest_verify-1.1.1.dist-info/top_level.txt
pytest_verify-1.1.1.dist-info/RECORD
