Metadata-Version: 2.4
Name: pytest-verify
Version: 1.1.1
Summary: A pytest plugin for snapshot verification with optional visual diff viewer.
Author-email: Mohamed Tahri <simotahri1@gmail.com>
License:                                  Apache License
Project-URL: Homepage, https://github.com/metahris/pytest-verify
Project-URL: Repository, https://github.com/metahris/pytest-verify
Project-URL: Stars, https://github.com/metahris/pytest-verify/stargazers
Project-URL: Forks, https://github.com/metahris/pytest-verify/network/members
Project-URL: Documentation, https://github.com/metahris/pytest-verify#readme
Project-URL: Issues, https://github.com/metahris/pytest-verify/issues
Project-URL: Changelog, https://github.com/metahris/pytest-verify/releases
Project-URL: DiffViewer, https://github.com/metahris/pytest-verify/tree/master/verify-diff-viewer
Keywords: pytest,snapshot,testing,verify,diff,viewer
Classifier: Development Status :: 5 - Production/Stable
Classifier: Framework :: Pytest
Classifier: Intended Audience :: Developers
Classifier: Topic :: Software Development :: Testing
Classifier: Programming Language :: Python :: 3
Classifier: Programming Language :: Python :: 3.9
Classifier: Programming Language :: Python :: 3.10
Classifier: Programming Language :: Python :: 3.11
Classifier: License :: OSI Approved :: Apache Software License
Requires-Python: >=3.9
License-File: LICENSE
Requires-Dist: click>=8.0
Requires-Dist: rich>=13.0
Requires-Dist: PyYAML>=6.0
Requires-Dist: dictlens
Requires-Dist: xmllens
Provides-Extra: pydantic
Requires-Dist: pydantic<3.0,>=2.0; extra == "pydantic"
Provides-Extra: numpy
Requires-Dist: numpy>=1.24; extra == "numpy"
Provides-Extra: pandas
Requires-Dist: pandas>=2.0; extra == "pandas"
Provides-Extra: data
Requires-Dist: pandas>=2.0; extra == "data"
Requires-Dist: numpy>=1.24; extra == "data"
Requires-Dist: pydantic>=2.0; extra == "data"
Provides-Extra: all
Requires-Dist: pydantic<3.0,>=2.0; extra == "all"
Requires-Dist: numpy>=1.24; extra == "all"
Requires-Dist: pandas>=2.0; extra == "all"
Dynamic: license-file
